ducktools/classbuilder/__init__.py
ducktools/classbuilder/__init__.pyi
ducktools/classbuilder/_version.py
ducktools/classbuilder/annotations.pyi
ducktools/classbuilder/prefab.py
ducktools/classbuilder/prefab.pyi
ducktools/classbuilder/py.typed
ducktools/classbuilder/annotations/__init__.py
ducktools/classbuilder/annotations/annotations_314.py
ducktools/classbuilder/annotations/annotations_pre_314.py
ducktools_classbuilder-0.12.3.dist-info/licenses/LICENSE
ducktools_classbuilder-0.12.3.dist-info/METADATA
ducktools_classbuilder-0.12.3.dist-info/WHEEL
ducktools_classbuilder-0.12.3.dist-info/top_level.txt
ducktools_classbuilder-0.12.3.dist-info/RECORD
