Metadata-Version: 2.4
Name: ducktools-classbuilder
Version: 0.12.3
Summary: Toolkit for creating class boilerplate generators
Author: David C Ellis
License-Expression: MIT
Project-URL: Homepage, https://github.com/davidcellis/ducktools-classbuilder
Classifier: Development Status :: 4 - Beta
Classifier: Programming Language :: Python :: 3.10
Classifier: Programming Language :: Python :: 3.11
Classifier: Programming Language :: Python :: 3.12
Classifier: Programming Language :: Python :: 3.13
Classifier: Programming Language :: Python :: 3.14
Classifier: Operating System :: OS Independent
Requires-Python: >=3.10
License-File: LICENSE
Provides-Extra: docs
Requires-Dist: sphinx>=8.1; extra == "docs"
Requires-Dist: myst-parser>=4.0; extra == "docs"
Requires-Dist: sphinx_rtd_theme>=3.0; extra == "docs"
Dynamic: license-file
